LICENSE
README.rst
pyproject.toml
setup.py
ygit.py
ygit.egg-info/PKG-INFO
ygit.egg-info/SOURCES.txt
ygit.egg-info/dependency_links.txt
ygit.egg-info/top_level.txt