Metadata-Version: 2.1
Name: ygit
Version: 0.4.0
Summary: A tiny (yocto) git client for MicroPython.
Home-page: https://github.com/keredson/ygit
Author: Derek Anderson
Author-email: public@kered.org
License: UNKNOWN
Platform: UNKNOWN
Classifier: Development Status :: 3 - Alpha
Classifier: Intended Audience :: Developers
Classifier: License :: OSI Approved :: GNU General Public License v3 (GPLv3)
Classifier: Operating System :: OS Independent
Classifier: Programming Language :: Python
Classifier: Programming Language :: Python :: 3
License-File: LICENSE
